md_merge/__init__.py
md_merge/__main__.py
md_merge/cli.py
md_merge/exceptions.py
md_merge/file_handler.py
md_merge/logger.py
md_merge/merger.py
md_merge-0.1.1.dist-info/METADATA
md_merge-0.1.1.dist-info/WHEEL
md_merge-0.1.1.dist-info/entry_points.txt
md_merge-0.1.1.dist-info/licenses/LICENSE
md_merge-0.1.1.dist-info/RECORD
