Metadata-Version: 2.4
Name: md-merge
Version: 0.1.1
Summary: A Python tool designed to take a list of Markdown files and merge them into a single document.
Project-URL: Homepage, https://github.com/difegam/md-merge
Project-URL: Bug Reports, https://github.com/difegam/md-merge/issues
Project-URL: Source, https://github.com/difegam/md-merge
Author-email: difegam <difegam3@gmail.com>
License-File: LICENSE
Keywords: markdown,markdown-merge,md-merge,merge,python-markdown
Classifier: License :: OSI Approved :: MIT License
Classifier: Operating System :: OS Independent
Classifier: Programming Language :: Python :: 3
Requires-Python: >=3.12
